higlass_data/__init__.py
higlass_data/conversions.py
higlass_data/create_cohort_vcf.py
higlass_data/create_coverage_bed.py
higlass_data/data/.DS_Store
higlass_data/data/__init__.py
higlass_data/data/hg38.chromsizes
higlass_data/data/hg38.mod.chromsizes
higlass_data/utils.py
cgap_higlass_data-0.4.0.dist-info/LICENSE
cgap_higlass_data-0.4.0.dist-info/METADATA
cgap_higlass_data-0.4.0.dist-info/WHEEL
cgap_higlass_data-0.4.0.dist-info/entry_points.txt
cgap_higlass_data-0.4.0.dist-info/RECORD
